Workbook

Sheet Dashboard
A1: The Essence Vault

Sheet Income Statement
A1: The Essence Vault
B2: Income Statement
B4: All figures in £ | D4: 2022A | E4: 2023A | F4: 2024A | G4: 2025F | H4: 2026F | I4: 2027F | J4: 2028F | K4: 2029F
B6: Revenues | D6: 14421276 | E6: 30095946 | F6: 34593327 | G6: =F6*(1+G24) -> 40474193 | H6: =G6*(1+H24) -> 47354805 | I6: =H6*(1+I24) -> 55405122 | J6: =I6*(1+J24) -> 64823993 | K6: =J6*(1+K24) -> 75844072
B7: COGS | D7: -10569992 | E7: -23778183 | F7: -26706251 | G7: =G6*G25*-1 -> -30355644 | H7: =H6*H25*-1 -> -35516104 | I7: =I6*I25*-1 -> -41553842 | J7: =J6*J25*-1 -> -48617995 | K7: =K6*K25*-1 -> -56883054
B8: Gorss Profit | D8: =SUM(D6:D7) -> 3851284 | E8: =SUM(E6:E7) -> 6317763 | F8: =SUM(F6:F7) -> 7887076 | G8: =SUM(G6:G7) -> 10118548 | H8: =SUM(H6:H7) -> 11838701 | I8: =SUM(I6:I7) -> 13851281 | J8: =SUM(J6:J7) -> 16205998 | K8: =SUM(K6:K7) -> 18961018
B10: Admin Expenses | D10: -2127491 | E10: -5541871 | F10: -7017148 | G10: =-G6*G27 -> -7285354.7 | H10: =-H6*H27 -> -8523865 | I10: =-I6*I27 -> -9972922 | J10: =-J6*J27 -> -11668319 | K10: =-K6*K27 -> -13651933
B11: Other Operating Income | D11: 449 | E11: 0 | F11: 0 | G11: 0 | H11: 0 | I11: 0 | J11: 0 | K11: 0
B12: Operating Profit | D12: =SUM(D8:D11) -> 1724242 | E12: =SUM(E8:E11) -> 775892 | F12: =SUM(F8:F11) -> 869928 | G12: =SUM(G8:G11) -> 2833193.5 | H12: =SUM(H8:H11) -> 3314836.4 | I12: =SUM(I8:I11) -> 3878358.6 | J12: =SUM(J8:J11) -> 4537679.5 | K12: =SUM(K8:K11) -> 5309085
B14: Other Interest Receiveable and similar income | D14: 0 | E14: 0 | F14: 7400 | G14: 0 | H14: 0 | I14: 0 | J14: 0 | K14: 0
B15: Interest Payables | D15: -94176 | E15: -400859 | F15: -1738151 | G15: =-(Assumptions!$C$5*(-'Balance Sheet'!F19)+(-'Balance Sheet'!F23))*Assumptions!$C$4 -> -771965 | H15: =-(Assumptions!$C$5*(-'Balance Sheet'!G19)+(-'Balance Sheet'!G23))*Assumptions!$C$4 -> -442900.02 | I15: =-(Assumptions!$C$5*(-'Balance Sheet'!H19)+(-'Balance Sheet'!H23))*Assumptions!$C$4 -> -517435.69 | J15: =-(Assumptions!$C$5*(-'Balance Sheet'!I19)+(-'Balance Sheet'!I23))*Assumptions!$C$4 -> -604642.42 | K15: =-(Assumptions!$C$5*(-'Balance Sheet'!J19)+(-'Balance Sheet'!J23))*Assumptions!$C$4 -> -706674.3
B16: Profit/loss Before Tax | D16: =SUM(D12:D15) -> 1630066 | E16: =SUM(E12:E15) -> 375033 | F16: =SUM(F12:F15) -> -860823 | G16: =SUM(G12:G15) -> 2061228.5 | H16: =SUM(H12:H15) -> 2871936.4 | I16: =SUM(I12:I15) -> 3360922.9 | J16: =SUM(J12:J15) -> 3933037.1 | K16: =SUM(K12:K15) -> 4602410.7
T17: Gross Margin | V17: =D8/D6 -> 0.2670557 | W17: =E8/E6 -> 0.20992073 | X17: =F8/F6 -> 0.22799414
B18: Tax on Profit | D18: -350734 | E18: 236765 | F18: -23678 | G18: =-G6*G28 -> -1214225.8 | H18: =-H6*H28 -> -1420644.2 | I18: =-I6*I28 -> -1662153.7 | J18: =-J6*J28 -> -1944719.8 | K18: =-K6*K28 -> -2275322.2 | T18: EBIT Margin | V18: =D12/D6 -> 0.11956237 | W18: =E12/E6 -> 0.025780615 | X18: =F12/F6 -> 0.025147278
B19: Profit for the financial year | D19: =SUM(D16:D18) -> 1279332 | E19: =SUM(E16:E18) -> 611798 | F19: =SUM(F16:F18) -> -884501 | G19: =SUM(G16:G18) -> 847002.7 | H19: =SUM(H16:H18) -> 1451292.2 | I19: =SUM(I16:I18) -> 1698769.2 | J19: =SUM(J16:J18) -> 1988317.3 | K19: =SUM(K16:K18) -> 2327088.6 | T19: EBT Margin | V19: =D16/D6 -> 0.11303202 | W19: =E16/E6 -> 0.012461246 | X19: =F16/F6 -> -0.024884077
T20: NET income margin | V20: =D19/D6 -> 0.088711429 | W20: =E19/E6 -> 0.020328253 | X20: =F19/F6 -> -0.025568544
B21: Drivers
B23: Revenue
B24: Revenue (% of growth) | E24: =E6/D6-1 -> 1.0869128 | F24: =F6/E6-1 -> 0.14943478 | G24: 0.17 | H24: 0.17 | I24: 0.17 | J24: 0.17 | K24: 0.17
B25: Cost of Sales % | D25: =-D7/D6 -> 0.7329443 | E25: =-E7/E6 -> 0.79007927 | F25: =-F7/F6 -> 0.77200586 | G25: 0.75 | H25: 0.75 | I25: 0.75 | J25: 0.75 | K25: 0.75
B27: Admin Expense (% of revenue) | D27: =-D10/D6 -> 0.14752446 | E27: =-E10/E6 -> 0.18414012 | F27: =-F10/F6 -> 0.20284687 | G27: 0.18 | H27: 0.18 | I27: 0.18 | J27: 0.18 | K27: 0.18
B28: Effective Tax Rate | D28: =-D18/D16 -> 0.21516552 | E28: =-E18/E16 -> -0.63131778 | F28: =-F18/F16 -> -0.027506235 | G28: 0.03 | H28: 0.03 | I28: 0.03 | J28: 0.03 | K28: 0.03

Sheet Balance Sheet
A1: The Essence Vault
B2: Balance Sheet
B4: All figures in £ | D4: 2022A | E4: 2023A | F4: 2024A | G4: 2025F | H4: 2026F | I4: 2027F | J4: 2028F | K4: 2029F
B6: Fixed Assets
B7: Intangible Assets | D7: 0 | E7: 23480 | F7: 21051 | G7: ='Dep CapEx'!G17 -> 18873.279 | H7: ='Dep CapEx'!H17 -> 16920.843 | I7: ='Dep CapEx'!I17 -> 15170.387 | J7: ='Dep CapEx'!J17 -> 13601.014 | K7: ='Dep CapEx'!K17 -> 12193.993
B8: Tangible Assets | D8: 1330925 | E8: 2784355 | F8: 1407186 | G8: ='Dep CapEx'!G13-'Balance Sheet'!G9-'Balance Sheet'!G10 -> 1409363.7 | H8: ='Dep CapEx'!H13-'Balance Sheet'!H9-'Balance Sheet'!H10 -> 1411316.2 | I8: ='Dep CapEx'!I13-'Balance Sheet'!I9-'Balance Sheet'!I10 -> 1413066.6 | J8: ='Dep CapEx'!J13-'Balance Sheet'!J9-'Balance Sheet'!J10 -> 1414636 | K8: ='Dep CapEx'!K13-'Balance Sheet'!K9-'Balance Sheet'!K10 -> 1416043
B9: Investment Property | D9: 153712 | E9: 153712 | F9: 153712 | G9: 153712 | H9: 153712 | I9: 153712 | J9: 153712 | K9: 153712
B10: Other Financial Assets | D10: 0 | E10: 15000 | F10: 15000 | G10: 15000 | H10: 15000 | I10: 15000 | J10: 15000 | K10: 15000
B11: Total Fixed Assets | D11: =SUM(D7:D10) -> 1484637 | E11: =SUM(E7:E10) -> 2976547 | F11: =SUM(F7:F10) -> 1596949 | G11: =SUM(G7:G10) -> 1596949 | H11: =SUM(H7:H10) -> 1596949 | I11: =SUM(I7:I10) -> 1596949 | J11: =SUM(J7:J10) -> 1596949 | K11: =SUM(K7:K10) -> 1596949
B13: Current Assets
B14: Stocks | D14: 846272 | E14: 2124876 | F14: 5828041 | G14: ='Working Capital'!G7 -> 5156301.2 | H14: ='Working Capital'!H7 -> 6032872.5 | I14: ='Working Capital'!I7 -> 7058460.8 | J14: ='Working Capital'!J7 -> 8258399.1 | K14: ='Working Capital'!K7 -> 9662327
B15: Debters | D15: 536545 | E15: 3534567 | F15: 11670285 | G15: ='Working Capital'!G6 -> 6653291.9 | H15: ='Working Capital'!H6 -> 7784351.6 | I15: ='Working Capital'!I6 -> 9107691.3 | J15: ='Working Capital'!J6 -> 10655999 | K15: ='Working Capital'!K6 -> 12467519
B16: Cash at Bank & in hand | D16: 1628512 | E16: 1398323 | F16: 704228 | G16: ='Cash Flow Statement'!G39 -> -499924.98 | H16: ='Cash Flow Statement'!H39 -> 696878.8 | I16: ='Cash Flow Statement'!I39 -> 2097896.5 | J16: ='Cash Flow Statement'!J39 -> 3737844.7 | K16: ='Cash Flow Statement'!K39 -> 5657341.3
B17: Total Current Assets | D17: =SUM(D14:D16) -> 3011329 | E17: =SUM(E14:E16) -> 7057766 | F17: =SUM(F14:F16) -> 18202554 | G17: =SUM(G14:G16) -> 11309668 | H17: =SUM(H14:H16) -> 14514103 | I17: =SUM(I14:I16) -> 18264049 | J17: =SUM(J14:J16) -> 22652243 | K17: =SUM(K14:K16) -> 27787187
B19: Creditors: Amounts falling due within 1 year | D19: -2036697 | E19: -7171027 | F19: -18052491 | G19: =-'Working Capital'!G8 -> -10312602 | H19: =-'Working Capital'!H8 -> -12065745 | I19: =-'Working Capital'!I8 -> -14116922 | J19: =-'Working Capital'!J8 -> -16516798 | K19: =-'Working Capital'!K8 -> -19324654
B20: Net Current Assets/(liabilities) | D20: =D17+D19 -> 974632 | E20: =E17+E19 -> -113261 | F20: =F17+F19 -> 150063 | G20: =G17+G19 -> 997065.7 | H20: =H17+H19 -> 2448357.9 | I20: =I17+I19 -> 4147127.1 | J20: =J17+J19 -> 6135444.4 | K20: =K17+K19 -> 8462533
B21: Totals Assets less current liabilities | D21: =D11+D17+D19 -> 2459269 | E21: =E11+E17+E19 -> 2863286 | F21: =F11+F17+F19 -> 1747012 | G21: =G11+G17+G19 -> 2594014.7 | H21: =H11+H17+H19 -> 4045306.9 | I21: =I11+I17+I19 -> 5744076.1 | J21: =J11+J17+J19 -> 7732393.4 | K21: =K11+K17+K19 -> 10059482
B23: Creditors: Amounts falling due after more than 1 year | D23: 0 | E23: 0 | F23: -44549 | G23: =-Assumptions!$C$9 -> -44549 | H23: =-Assumptions!$C$9 -> -44549 | I23: =-Assumptions!$C$9 -> -44549 | J23: =-Assumptions!$C$9 -> -44549 | K23: =-Assumptions!$C$9 -> -44549
B24: Provisions for liabilities | D24: -166466 | E24: -292503 | F24: -16181 | G24: =-Assumptions!$C$10 -> -16181 | H24: =-Assumptions!$C$10 -> -16181 | I24: =-Assumptions!$C$10 -> -16181 | J24: =-Assumptions!$C$10 -> -16181 | K24: =-Assumptions!$C$10 -> -16181
B25: Net Assets | D25: =D21+D24+D23 -> 2292803 | E25: =E21+E24+E23 -> 2570783 | F25: =F21+F24+F23 -> 1686282 | G25: =G21+G24+G23 -> 2533284.7 | H25: =H21+H24+H23 -> 3984576.9 | I25: =I21+I24+I23 -> 5683346.1 | J25: =J21+J24+J23 -> 7671663.4 | K25: =K21+K24+K23 -> 9998752
B27: Capital and Reserves
B28: Called up share Capital | D28: 100 | E28: 100 | F28: 100 | G28: 100 | H28: 100 | I28: 100 | J28: 100 | K28: 100
B29: Retained Earnings | D29: 2292703 | E29: 2570683 | F29: 1686182 | G29: =F29+'Income Statement'!G19+'Cash Flow Statement'!G34 -> 2533184.7 | H29: =G29+'Income Statement'!H19+'Cash Flow Statement'!H34 -> 3984476.9 | I29: =H29+'Income Statement'!I19+'Cash Flow Statement'!I34 -> 5683246.1 | J29: =I29+'Income Statement'!J19+'Cash Flow Statement'!J34 -> 7671563.4 | K29: =J29+'Income Statement'!K19+'Cash Flow Statement'!K34 -> 9998652
B30: Share holders Funds | D30: =SUM(D28:D29) -> 2292803 | E30: =SUM(E28:E29) -> 2570783 | F30: =SUM(F28:F29) -> 1686282 | G30: =SUM(G28:G29) -> 2533284.7 | H30: =SUM(H28:H29) -> 3984576.9 | I30: =SUM(I28:I29) -> 5683346.1 | J30: =SUM(J28:J29) -> 7671663.4 | K30: =SUM(K28:K29) -> 9998752
B32: Check | D32: =D25-D30 -> 0 | E32: =E25-E30 -> 0 | F32: =F25-F30 -> 0 | G32: =G25-G30 -> 0 | H32: =H25-H30 -> 0 | I32: =I25-I30 -> 0 | J32: =J25-J30 -> 0 | K32: =K25-K30 -> 0
B36: Liquidity Ratio
B37: Current Ratio | D37: =-D17/D19 -> 1.4785356 | E37: =-E17/E19 -> 0.98420575 | F37: =-F17/F19 -> 1.0083126
B38: Quick Ratio | D38: =-(D17-D14)/D19 -> 1.0630236 | E38: =-(E17-E14)/E19 -> 0.68789171 | F38: =-(F17-F14)/F19 -> 0.68547399
B39: Cash Ratio | D39: =-D16/D19 -> 0.79958482 | E39: =-E16/E19 -> 0.1949962 | F39: =-F16/F19 -> 0.039010018
B41: Leverage ratio
B42: Debt to Equity Ratio | D42: =-(D19+D23+D24)/D30 -> 0.96090375 | E42: =-(E19+E23+E24)/E30 -> 2.9032128 | F42: =-(F19+F23+F24)/F30 -> 10.741514
B44: ROE (Net Income/ ShareHolders Equity) | D44: ='Income Statement'!D19/'Balance Sheet'!D30 -> 0.55797729 | E44: ='Income Statement'!E19/'Balance Sheet'!E30 -> 0.23798119 | F44: ='Income Statement'!F19/'Balance Sheet'!F30 -> -0.52452733

Sheet Cash Flow Statement
A1: The Essence Vault
B2: Cashflow Statement
B4: All figures in £ | D4: 2022A | E4: 2023A | F4: 2024A | G4: 2025F | H4: 2026F | I4: 2027F | J4: 2028F | K4: 2029F
B6: Cash flow from operating activities
B7: Profit for the year | G7: ='Income Statement'!G19 -> 847002.7 | H7: ='Income Statement'!H19 -> 1451292.2 | I7: ='Income Statement'!I19 -> 1698769.2 | J7: ='Income Statement'!J19 -> 1988317.3 | K7: ='Income Statement'!K19 -> 2327088.6
B8: Adjustments to cash flows from non-cash items
B9: Depreciation and amortisation | G9: ='Dep CapEx'!G7+('Balance Sheet'!F7-'Balance Sheet'!G7) -> 285497.07 | H9: ='Dep CapEx'!H7+('Balance Sheet'!G7-'Balance Sheet'!H7) -> 333436.07 | I9: ='Dep CapEx'!I7+('Balance Sheet'!H7-'Balance Sheet'!I7) -> 389586.31 | J9: ='Dep CapEx'!J7+('Balance Sheet'!I7-'Balance Sheet'!J7) -> 455337.32 | K9: ='Dep CapEx'!K7+('Balance Sheet'!J7-'Balance Sheet'!K7) -> 532315.52
B10: Finance costs | G10: =-'Income Statement'!G15 -> 771965 | H10: =-'Income Statement'!H15 -> 442900.02 | I10: =-'Income Statement'!I15 -> 517435.69 | J10: =-'Income Statement'!J15 -> 604642.42 | K10: =-'Income Statement'!K15 -> 706674.3
B11: Taxation charge | G11: =-'Income Statement'!G18 -> 1214225.8 | H11: =-'Income Statement'!H18 -> 1420644.2 | I11: =-'Income Statement'!I18 -> 1662153.7 | J11: =-'Income Statement'!J18 -> 1944719.8 | K11: =-'Income Statement'!K18 -> 2275322.2
B14: Working capital adjustments
B15: Increase in stocks | G15: ='Working Capital'!F7-'Working Capital'!G7 -> 671739.75 | H15: ='Working Capital'!G7-'Working Capital'!H7 -> -876571.21 | I15: ='Working Capital'!H7-'Working Capital'!I7 -> -1025588.3 | J15: ='Working Capital'!I7-'Working Capital'!J7 -> -1199938.3 | K15: ='Working Capital'!J7-'Working Capital'!K7 -> -1403927.8
B16: Increase in trade debtors | G16: ='Working Capital'!F6-'Working Capital'!G6 -> 5016993.1 | H16: ='Working Capital'!G6-'Working Capital'!H6 -> -1131059.6 | I16: ='Working Capital'!H6-'Working Capital'!I6 -> -1323339.8 | J16: ='Working Capital'!I6-'Working Capital'!J6 -> -1548307.5 | K16: ='Working Capital'!J6-'Working Capital'!K6 -> -1811519.8
B17: Increase in trade creditors | G17: ='Working Capital'!G8-'Working Capital'!F8 -> -7739888.5 | H17: ='Working Capital'!H8-'Working Capital'!G8 -> 1753142.4 | I17: ='Working Capital'!I8-'Working Capital'!H8 -> 2051176.6 | J17: ='Working Capital'!J8-'Working Capital'!I8 -> 2399876.7 | K17: ='Working Capital'!K8-'Working Capital'!J8 -> 2807855.7
B19: Cash generated from operating activity | G19: =SUM(G7:G17) -> 1067534.9 | H19: =SUM(H7:H17) -> 3393784 | I19: =SUM(I7:I17) -> 3970193.4 | J19: =SUM(J7:J17) -> 4644647.6 | K19: =SUM(K7:K17) -> 5433808.6
B20: Income tax paid | G20: ='Income Statement'!G18 -> -1214225.8 | H20: ='Income Statement'!H18 -> -1420644.2 | I20: ='Income Statement'!I18 -> -1662153.7 | J20: ='Income Statement'!J18 -> -1944719.8 | K20: ='Income Statement'!K18 -> -2275322.2
B22: Net cash flow from operating activities | G22: =SUM(G19:G21) -> -146690.91 | H22: =SUM(H19:H21) -> 1973139.9 | I22: =SUM(I19:I21) -> 2308039.8 | J22: =SUM(J19:J21) -> 2699927.9 | K22: =SUM(K19:K21) -> 3158486.4
B23: Acquisitions of tangible assets | G23: =-'Dep CapEx'!G11 -> -285497.07 | H23: =-'Dep CapEx'!H11 -> -333436.07 | I23: =-'Dep CapEx'!I11 -> -389586.31 | J23: =-'Dep CapEx'!J11 -> -455337.32 | K23: =-'Dep CapEx'!K11 -> -532315.52
B24: Acquisitions of intangible assets | G24: =0 -> 0 | H24: =0 -> 0 | I24: =0 -> 0 | J24: =0 -> 0 | K24: =0 -> 0
B25: Acquisitions of investment properties | G25: =0 -> 0 | H25: =0 -> 0 | I25: =0 -> 0 | J25: =0 -> 0 | K25: =0 -> 0
B26: Acquisitions of other investments | G26: =0 -> 0 | H26: =0 -> 0 | I26: =0 -> 0 | J26: =0 -> 0 | K26: =0 -> 0
B28: Net cashflows from investing activities | G28: =SUM(G23:G26) -> -285497.07 | H28: =SUM(H23:H26) -> -333436.07 | I28: =SUM(I23:I26) -> -389586.31 | J28: =SUM(J23:J26) -> -455337.32 | K28: =SUM(K23:K26) -> -532315.52
B30: Cash flows from financing activities
B31: Interest Paid | G31: ='Income Statement'!G15 -> -771965 | H31: ='Income Statement'!H15 -> -442900.02 | I31: ='Income Statement'!I15 -> -517435.69 | J31: ='Income Statement'!J15 -> -604642.42 | K31: ='Income Statement'!K15 -> -706674.3
B32: Proceeds from other borrowings draw downs | G32: =0 -> 0 | H32: =0 -> 0 | I32: =0 -> 0 | J32: =0 -> 0 | K32: =0 -> 0
B33: Repayment of other borrowing | G33: =0 -> 0 | H33: =0 -> 0 | I33: =0 -> 0 | J33: =0 -> 0 | K33: =0 -> 0
B34: Dividends paid | G34: =-'Income Statement'!G19*Assumptions!$C$6 -> 0 | H34: =-'Income Statement'!H19*Assumptions!$C$6 -> 0 | I34: =-'Income Statement'!I19*Assumptions!$C$6 -> 0 | J34: =-'Income Statement'!J19*Assumptions!$C$6 -> 0 | K34: =-'Income Statement'!K19*Assumptions!$C$6 -> 0
B35: Net cash flows from financing activities | G35: =SUM(G31:G34) -> -771965 | H35: =SUM(H31:H34) -> -442900.02 | I35: =SUM(I31:I34) -> -517435.69 | J35: =SUM(J31:J34) -> -604642.42 | K35: =SUM(K31:K34) -> -706674.3
B36: Net (Decrease)/Increase in cash and cash equivalents | G36: =G22+G28+G35 -> -1204153 | H36: =H22+H28+H35 -> 1196803.8 | I36: =I22+I28+I35 -> 1401017.8 | J36: =J22+J28+J35 -> 1639948.1 | K36: =K22+K28+K35 -> 1919496.6
B38: Cash and Cash equivalents at 1 January | G38: ='Balance Sheet'!F16 -> 704228 | H38: =G39 -> -499924.98 | I38: =H39 -> 696878.8 | J38: =I39 -> 2097896.5 | K38: =J39 -> 3737844.7
B39: Cash and cash equivalents at 31 December | G39: =G38+G36 -> -499924.98 | H39: =H38+H36 -> 696878.8 | I39: =I38+I36 -> 2097896.5 | J39: =J38+J36 -> 3737844.7 | K39: =K38+K36 -> 5657341.3

Sheet Dep CapEx
B1: The Essence Vault
B3: All figures in £ | D3: 2022A | E3: 2023A | F3: 2024A | G3: 2025F | H3: 2026F | I3: 2027F | J3: 2028F | K3: 2029F
B5: Revenue | D5: ='Income Statement'!D6 -> 14421276 | E5: ='Income Statement'!E6 -> 30095946 | F5: ='Income Statement'!F6 -> 34593327 | G5: ='Income Statement'!G6 -> 40474193 | H5: ='Income Statement'!H6 -> 47354805 | I5: ='Income Statement'!I6 -> 55405122 | J5: ='Income Statement'!J6 -> 64823993 | K5: ='Income Statement'!K6 -> 75844072
B7: Depreciation | D7: ='Cash Flow Statement'!D9 -> 0 | E7: ='Cash Flow Statement'!E9 -> 0 | F7: ='Cash Flow Statement'!F9 -> 0 | G7: =G5*G8 -> 283319.35 | H7: =H5*H8 -> 331483.64 | I7: =I5*I8 -> 387835.86 | J7: =J5*J8 -> 453767.95 | K7: =K5*K8 -> 530908.5
B8: Depreciation as % or revenue | G8: 0.007 | H8: 0.007 | I8: 0.007 | J8: 0.007 | K8: 0.007
B10: Beginning PP&E | G10: =F13 -> 1575898 | H10: =G13 -> 1578075.7 | I10: =H13 -> 1580028.2 | J10: =I13 -> 1581778.6 | K10: =J13 -> 1583348
B11: Capital Expenditure | G11: =G12+(F17-G17) -> 285497.07 | H11: =H12+(G17-H17) -> 333436.07 | I11: =I12+(H17-I17) -> 389586.31 | J11: =J12+(I17-J17) -> 455337.32 | K11: =K12+(J17-K17) -> 532315.52
B12: Depreciation | G12: =G7 -> 283319.35 | H12: =H7 -> 331483.64 | I12: =I7 -> 387835.86 | J12: =J7 -> 453767.95 | K12: =K7 -> 530908.5
B13: Net PPE | F13: ='Balance Sheet'!F8+'Balance Sheet'!F9+'Balance Sheet'!F10 -> 1575898 | G13: =G10+G11-G12 -> 1578075.7 | H13: =H10+H11-H12 -> 1580028.2 | I13: =I10+I11-I12 -> 1581778.6 | J13: =J10+J11-J12 -> 1583348 | K13: =K10+K11-K12 -> 1584755
B17: Ammortisation | E17: ='Balance Sheet'!E7 -> 23480 | F17: ='Balance Sheet'!F7 -> 21051 | G17: =F17*(1-$C$19) -> 18873.279 | H17: =G17*(1-$C$19) -> 16920.843 | I17: =H17*(1-$C$19) -> 15170.387 | J17: =I17*(1-$C$19) -> 13601.014 | K17: =J17*(1-$C$19) -> 12193.993
B19: Ammortisation % | C19: =('Balance Sheet'!E7-'Balance Sheet'!F7)/'Balance Sheet'!E7 -> 0.10344974

Sheet Working Capital
A1: The Essence Vault
B2: Working Capital
B4: All figures in £ | D4: 2022A | E4: 2023A | F4: 2024A | G4: 2025F | H4: 2026F | I4: 2027F | J4: 2028F | K4: 2029F
B6: Accounts Receivables | D6: ='Balance Sheet'!D15 -> 536545 | E6: ='Balance Sheet'!E15 -> 3534567 | F6: ='Balance Sheet'!F15 -> 11670285 | G6: =G10/G14 -> 6653291.9 | H6: =H10/H14 -> 7784351.6 | I6: =I10/I14 -> 9107691.3 | J6: =J10/J14 -> 10655999 | K6: =K10/K14 -> 12467519
B7: Stocks | D7: ='Balance Sheet'!D14 -> 846272 | E7: ='Balance Sheet'!E14 -> 2124876 | F7: ='Balance Sheet'!F14 -> 5828041 | G7: =G11/G15 -> 5156301.2 | H7: =H11/H15 -> 6032872.5 | I7: =I11/I15 -> 7058460.8 | J7: =J11/J15 -> 8258399.1 | K7: =K11/K15 -> 9662327
B8: Accounts Payables | D8: =-'Balance Sheet'!D19 -> 2036697 | E8: =-'Balance Sheet'!E19 -> 7171027 | F8: =-'Balance Sheet'!F19 -> 18052491 | G8: =G11/G16 -> 10312602 | H8: =H11/H16 -> 12065745 | I8: =I11/I16 -> 14116922 | J8: =J11/J16 -> 16516798 | K8: =K11/K16 -> 19324654
B10: Total Revenue | D10: ='Income Statement'!D6 -> 14421276 | E10: ='Income Statement'!E6 -> 30095946 | F10: ='Income Statement'!F6 -> 34593327 | G10: ='Income Statement'!G6 -> 40474193 | H10: ='Income Statement'!H6 -> 47354805 | I10: ='Income Statement'!I6 -> 55405122 | J10: ='Income Statement'!J6 -> 64823993 | K10: ='Income Statement'!K6 -> 75844072
B11: Operating Costs | D11: =('Income Statement'!D7+'Income Statement'!D10)*-1 -> 12697483 | E11: =('Income Statement'!E7+'Income Statement'!E10)*-1 -> 29320054 | F11: =('Income Statement'!F7+'Income Statement'!F10)*-1 -> 33723399 | G11: =('Income Statement'!G7+'Income Statement'!G10)*-1 -> 37640999 | H11: =('Income Statement'!H7+'Income Statement'!H10)*-1 -> 44039969 | I11: =('Income Statement'!I7+'Income Statement'!I10)*-1 -> 51526764 | J11: =('Income Statement'!J7+'Income Statement'!J10)*-1 -> 60286314 | K11: =('Income Statement'!K7+'Income Statement'!K10)*-1 -> 70534987
B13: Turnover Ratios
B14: Receivables turnover | D14: =D10/D6 -> 26.878036 | E14: =E10/E6 -> 8.5147476 | F14: =F10/F6 -> 2.964223 | G14: =365/G18 -> 6.0833333 | H14: =365/H18 -> 6.0833333 | I14: =365/I18 -> 6.0833333 | J14: =365/J18 -> 6.0833333 | K14: =365/K18 -> 6.0833333
B15: Stocks turnover | D15: =D11/D7 -> 15.004021 | E15: =E11/E7 -> 13.798478 | F15: =F11/F7 -> 5.7864039 | G15: =365/G19 -> 7.3 | H15: =365/H19 -> 7.3 | I15: =365/I19 -> 7.3 | J15: =365/J19 -> 7.3 | K15: =365/K19 -> 7.3
B16: Payables turnover | D16: =D11/D8 -> 6.2343505 | E16: =E11/E8 -> 4.0886827 | F16: =F11/F8 -> 1.8680745 | G16: =365/G20 -> 3.65 | H16: =365/H20 -> 3.65 | I16: =365/I20 -> 3.65 | J16: =365/J20 -> 3.65 | K16: =365/K20 -> 3.65
B18: Receivables collection period | D18: =365/D14 -> 13.579861 | E18: =365/E14 -> 42.866802 | F18: =365/F14 -> 123.13514 | G18: 60 | H18: 60 | I18: 60 | J18: 60 | K18: 60
B19: Inventory processing period | D19: =365/D15 -> 24.326812 | E19: =365/E15 -> 26.452193 | F19: =365/F15 -> 63.078902 | G19: 50 | H19: 50 | I19: 50 | J19: 50 | K19: 50
B20: Payment period | D20: =365/D16 -> 58.546596 | E20: =365/E16 -> 89.270806 | F20: =365/F16 -> 195.38835 | G20: 100 | H20: 100 | I20: 100 | J20: 100 | K20: 100
B21: Cash collection cycle | D21: =D18+D19-D20 -> -20.639923 | E21: =E18+E19-E20 -> -19.951811 | F21: =F18+F19-F20 -> -9.1743103 | G21: =G18+G19-G20 -> 10 | H21: =H18+H19-H20 -> 10 | I21: =I18+I19-I20 -> 10 | J21: =J18+J19-J20 -> 10 | K21: =K18+K19-K20 -> 10

Sheet Assumptions
A1: The Essence Vault
B3: Financing assumptions
B4: Interest rate on borrowings | C4: 0.1
B5: Interest-bearing % of Creditors (within 1yr) | C5: 0.42515468
B6: Dividend payout (% of profit) | C6: 0
B8: Balance-held-flat assumptions
B9: Creditors: due after 1 year (held flat, £) | C9: 44549
B10: Provisions for liabilities (held flat, £) | C10: 16181
